{"placeDataList":[{"place":"vvvv","lastUpdateTime_forSave":{"year":2019,"month":12,"day":2,"hour":19,"minute":52,"second":50},"cleanInterval_forSave":{"year":0,"month":0,"day":2,"hour":0,"minute":0,"second":0}},{"place":"a","lastUpdateTime_forSave":{"year":2019,"month":12,"day":2,"hour":19,"minute":23,"second":46},"cleanInterval_forSave":{"year":0,"month":0,"day":3,"hour":0,"minute":0,"second":0}},{"place":"v","lastUpdateTime_forSave":{"year":2019,"month":12,"day":2,"hour":19,"minute":23,"second":51},"cleanInterval_forSave":{"year":0,"month":0,"day":4,"hour":0,"minute":0,"second":0}},{"place":"s","lastUpdateTime_forSave":{"year":2019,"month":12,"day":2,"hour":19,"minute":23,"second":55},"cleanInterval_forSave":{"year":0,"month":0,"day":2,"hour":0,"minute":0,"second":0}}]}